openpgpcard_x25519_agent/__init__.py
openpgpcard_x25519_agent/card.py
openpgpcard_x25519_agent/cli.py
openpgpcard_x25519_agent/client.py
openpgpcard_x25519_agent/client_cli.py
openpgpcard_x25519_agent/cnf.py
openpgpcard_x25519_agent/kdf.py
openpgpcard_x25519_agent/msg.py
openpgpcard_x25519_agent/server.py
openpgpcard_x25519_agent-1.2.0.dist-info/METADATA
openpgpcard_x25519_agent-1.2.0.dist-info/WHEEL
openpgpcard_x25519_agent-1.2.0.dist-info/entry_points.txt
openpgpcard_x25519_agent-1.2.0.dist-info/licenses/LICENSE
openpgpcard_x25519_agent-1.2.0.dist-info/RECORD
