Metadata-Version: 2.4
Name: openpgpcard-x25519-agent
Version: 1.2.0
Summary: Socket interface to Curve25519 ECDH from an OpenPGP card.
Project-URL: source, https://git.sr.ht/~arx10/openpgpcard-x25519-agent
Project-URL: issues, https://todo.sr.ht/~arx10/openpgpcard-x25519-agent
Project-URL: mailing-list, https://lists.sr.ht/~arx10/openpgpcard-x25519-agent
Author-email: Arcem Tene <dev@arcemtene.com>
License:                     GNU GENERAL PUBLIC LICENSE
License-File: LICENSE
Classifier: Development Status :: 4 - Beta
Classifier: Environment :: Console
Classifier: Operating System :: POSIX
Classifier: Programming Language :: Python
Classifier: Topic :: Security :: Cryptography
Classifier: Topic :: System :: Hardware :: Universal Serial Bus (USB) :: Smart Card
Requires-Python: >=3.8
Requires-Dist: docopt-ng~=0.9
Requires-Dist: openpgppy~=1.2
Requires-Dist: pyscard~=2.0
